m2w/__init__.py
m2w/json2.py
m2w/math.py
m2w/md5.py
m2w/up.py
m2w/up_password.py
m2w/update.py
m2w/upload.py
m2w/wp.py
m2w/config/__init__.py
m2w/config/config.py
m2w/password/__init__.py
m2w/password/detector.py
m2w/password/uploader.py
m2w/rest_api/__init__.py
m2w/rest_api/articles.py
m2w/rest_api/categories.py
m2w/rest_api/create.py
m2w/rest_api/progress_manager.py
m2w/rest_api/rate_limiter.py
m2w/rest_api/rest_api.py
m2w/rest_api/tags.py
m2w/rest_api/update.py
m2w/rest_api/utils.py
m2w-2.7.2.dist-info/licenses/license.txt
m2w-2.7.2.dist-info/METADATA
m2w-2.7.2.dist-info/WHEEL
m2w-2.7.2.dist-info/top_level.txt
m2w-2.7.2.dist-info/RECORD
