Metadata-Version: 2.4
Name: m2w
Version: 2.7.2
Summary: Automatically upload and update local markdown to WordPress via Python
Author-email: huangwb8 <hwb2012@qq.com>, FoxSuzuran <2903582631@qq.com>
License: The MIT License (MIT)
Project-URL: Homepage, https://github.com/huangwb8/m2w
Project-URL: Documentation, https://github.com/huangwb8/m2w#readme
Project-URL: Source, https://github.com/huangwb8/m2w
Project-URL: Bug-Tracker, https://github.com/huangwb8/m2w/issues
Keywords: markdown,wordpress,xmlrpc,rest-api,blog
Classifier: Development Status :: 4 - Beta
Classifier: Intended Audience :: Developers
Classifier: License :: OSI Approved :: MIT License
Classifier: Programming Language :: Python :: 3
Classifier: Programming Language :: Python :: 3 :: Only
Classifier: Programming Language :: Python :: 3.7
Classifier: Programming Language :: Python :: 3.8
Classifier: Programming Language :: Python :: 3.9
Classifier: Programming Language :: Python :: 3.10
Classifier: Programming Language :: Python :: 3.11
Classifier: Operating System :: OS Independent
Requires-Python: >=3.7.6
License-File: license.txt
Requires-Dist: python-frontmatter>=1.0.0
Requires-Dist: markdown>=3.3.6
Requires-Dist: python-wordpress-xmlrpc>=2.3
Requires-Dist: httpx>=0.24.0
Provides-Extra: admonition
Requires-Dist: markdown-gfm-admonition>=0.1.0; extra == "admonition"
Dynamic: license-file
